{
  "month_end": "2024-02-29",
  "trade_date": "2024-03-01",
  "cohort_id": 2,
  "weights_ls": {
    "BRFS3": 0.022727272727272728,
    "CEAB3": 0.022727272727272728,
    "IRBR3": 0.022727272727272728,
    "LIGT3": 0.022727272727272728,
    "OPCT3": 0.022727272727272728,
    "PETR4": 0.022727272727272728,
    "PLPL3": 0.022727272727272728,
    "POMO4": 0.022727272727272728,
    "RANI3": 0.022727272727272728,
    "SOJA3": 0.022727272727272728,
    "TEND3": 0.022727272727272728,
    "UGPA3": 0.022727272727272728,
    "VLID3": 0.022727272727272728,
    "VULC3": 0.022727272727272728,
    "YDUQ3": 0.022727272727272728,
    "ONCO3": 0.022727272727272728,
    "BBAS3": 0.022727272727272728,
    "KEPL3": 0.022727272727272728,
    "NEOE3": 0.022727272727272728,
    "UNIP6": 0.022727272727272728,
    "CXSE3": 0.022727272727272728,
    "TASA4": 0.022727272727272728,
    "AERI3": -0.02,
    "AMBP3": -0.02,
    "BEEF3": -0.02,
    "BHIA3": -0.02,
    "BLAU3": -0.02,
    "CBAV3": -0.02,
    "GFSA3": -0.02,
    "HAPV3": -0.02,
    "JHSF3": -0.02,
    "OIBR3": -0.02,
    "QUAL3": -0.02,
    "RCSL4": -0.02,
    "RECV3": -0.02,
    "SEQL3": -0.02,
    "VAMO3": -0.02,
    "WIZC3": -0.02,
    "SRNA3": -0.02,
    "ALPA4": -0.02,
    "DASA3": -0.02,
    "MLAS3": -0.02,
    "SUZB3": -0.02,
    "ANIM3": -0.02,
    "ENEV3": -0.02,
    "MYPK3": -0.02,
    "VITT3": -0.02
  },
  "weights_d10": {
    "BBAS3": 0.043478260869565216,
    "BRFS3": 0.043478260869565216,
    "CEAB3": 0.043478260869565216,
    "CXSE3": 0.043478260869565216,
    "IRBR3": 0.043478260869565216,
    "KEPL3": 0.043478260869565216,
    "LIGT3": 0.043478260869565216,
    "NEOE3": 0.043478260869565216,
    "ONCO3": 0.043478260869565216,
    "OPCT3": 0.043478260869565216,
    "PETR4": 0.043478260869565216,
    "PLPL3": 0.043478260869565216,
    "POMO4": 0.043478260869565216,
    "RANI3": 0.043478260869565216,
    "SOJA3": 0.043478260869565216,
    "TASA4": 0.043478260869565216,
    "TEND3": 0.043478260869565216,
    "TTEN3": 0.043478260869565216,
    "UGPA3": 0.043478260869565216,
    "UNIP6": 0.043478260869565216,
    "VLID3": 0.043478260869565216,
    "VULC3": 0.043478260869565216,
    "YDUQ3": 0.043478260869565216
  },
  "dur_long": {
    "TASA4": 3,
    "RANI3": 18,
    "UGPA3": 6,
    "VULC3": 15,
    "POMO4": 6,
    "CXSE3": 9,
    "BBAS3": 3,
    "PLPL3": 9,
    "PETR4": 3,
    "BRFS3": 3,
    "TEND3": 3,
    "VLID3": 3,
    "IRBR3": 3,
    "KEPL3": 3,
    "LIGT3": 6,
    "CEAB3": 6,
    "SOJA3": 3,
    "OPCT3": 6,
    "NEOE3": 6,
    "YDUQ3": 3,
    "ONCO3": 9,
    "UNIP6": 3
  },
  "dur_short": {
    "OIBR3": 15,
    "GFSA3": 9,
    "MYPK3": 9,
    "RCSL4": 3,
    "JHSF3": 6,
    "SRNA3": 3,
    "QUAL3": 15,
    "DASA3": 27,
    "BLAU3": 6,
    "MLAS3": 3,
    "ALPA4": 24,
    "CBAV3": 12,
    "VITT3": 3,
    "RECV3": 3,
    "SEQL3": 21,
    "VAMO3": 3,
    "AMBP3": 3,
    "SUZB3": 6,
    "BHIA3": 3,
    "AERI3": 18,
    "ANIM3": 3,
    "ENEV3": 6,
    "WIZC3": 6,
    "BEEF3": 3,
    "HAPV3": 12
  },
  "strikes_long": {
    "LPSB3": 1,
    "MPLU3": 2,
    "LIGT3": 1,
    "CTIP3": 1,
    "VLID3": 2,
    "JHSF3": 1,
    "TAEE11": 1,
    "COCE5": 1,
    "ARTR3": 1,
    "PSSA3": 1,
    "BRFS3": 1,
    "MRVE3": 1,
    "SMTO3": 1,
    "CVCB3": 2,
    "LINX3": 2,
    "POMO4": 1,
    "MDIA3": 1,
    "FLRY3": 1,
    "BRAP4": 2,
    "SMLS3": 1,
    "ENGI11": 1,
    "PRIO3": 2,
    "ENAT3": 1,
    "RENT3": 1,
    "DXCO3": 1,
    "CSMG3": 1,
    "LCAM3": 3,
    "ELET3": 1,
    "JBSS3": 1,
    "CPLE6": 1,
    "SRNA3": 2,
    "CSNA3": 2,
    "MGLU3": 1,
    "MRFG3": 1,
    "PETZ3": 1,
    "VALE3": 1,
    "RADL3": 1,
    "INTB3": 1,
    "AALR3": 1,
    "ONCO3": 1,
    "CXSE3": 1
  },
  "strikes_short": {
    "CYRE3": 1,
    "HYPE3": 1,
    "BRFS3": 1,
    "PRIO3": 1,
    "CSNA3": 2,
    "MPLU3": 1,
    "AZZA3": 1,
    "AMAR3": 1,
    "TGMA3": 1,
    "SBSP3": 1,
    "ENBR3": 1,
    "DXCO3": 1,
    "MYPK3": 2,
    "ARTR3": 1,
    "CSMG3": 1,
    "BRSR6": 1,
    "GOAU4": 1,
    "AMER3": 1,
    "DAGB33": 1,
    "MOTV3": 1,
    "LEVE3": 1,
    "SMTO3": 1,
    "POMO4": 1,
    "ECOR3": 1,
    "SRNA3": 1,
    "VULC3": 1,
    "CAML3": 1,
    "DMMO3": 1,
    "LPSB3": 1,
    "HBOR3": 1,
    "SAPR11": 1,
    "LAME3": 1,
    "IRBR3": 1,
    "AZUL4": 2,
    "MGLU3": 1,
    "GFSA3": 1,
    "ALPA4": 1,
    "SEER3": 1,
    "TAEE11": 1,
    "VITT3": 1,
    "DASA3": 1
  },
  "ls_target_counts": {
    "long": 0,
    "short": 0
  }
}